pyuff_ustb/__init__.py
pyuff_ustb/common.py
pyuff_ustb/objects/__init__.py
pyuff_ustb/objects/apodization.py
pyuff_ustb/objects/beamformed_data.py
pyuff_ustb/objects/channel_data.py
pyuff_ustb/objects/phantom.py
pyuff_ustb/objects/point.py
pyuff_ustb/objects/pulse.py
pyuff_ustb/objects/uff.py
pyuff_ustb/objects/wave.py
pyuff_ustb/objects/wavefront.py
pyuff_ustb/objects/window.py
pyuff_ustb/objects/probes/__init__.py
pyuff_ustb/objects/probes/curvilinear_array.py
pyuff_ustb/objects/probes/curvilinear_matrix_array.py
pyuff_ustb/objects/probes/linear_array.py
pyuff_ustb/objects/probes/matrix_array.py
pyuff_ustb/objects/probes/probe.py
pyuff_ustb/objects/scans/__init__.py
pyuff_ustb/objects/scans/linear_3D_scan.py
pyuff_ustb/objects/scans/linear_scan.py
pyuff_ustb/objects/scans/linear_scan_rotated.py
pyuff_ustb/objects/scans/scan.py
pyuff_ustb/objects/scans/sector_scan.py
pyuff_ustb/readers/__init__.py
pyuff_ustb/readers/base.py
pyuff_ustb/readers/util.py
pyuff_ustb-3.0.0.dist-info/METADATA
pyuff_ustb-3.0.0.dist-info/WHEEL
pyuff_ustb-3.0.0.dist-info/licenses/LICENSE
pyuff_ustb-3.0.0.dist-info/RECORD
