Metadata-Version: 2.3
Name: pyuff_ustb
Version: 3.0.0
Summary: An implementation of USTB's ultrasound file format (UFF) in Python.
Project-URL: Bug Tracker, https://github.com/magnusdk/pyuff_ustb/issues
Project-URL: Homepage, https://pyuff-ustb.readthedocs.io/en/latest/
Author-email: Magnus Dalen Kvalevåg <magnus.kvalevag@ntnu.no>
License-File: LICENSE
Classifier: License :: OSI Approved :: Apache Software License
Classifier: Operating System :: OS Independent
Classifier: Programming Language :: Python :: 3
Requires-Python: >=3.9
Requires-Dist: h5py
Requires-Dist: numpy
